README.md
setup.py
bin/codeframe
codeframe/__init__.py
codeframe/cmd_parser.py
codeframe/config.py
codeframe/df_table.py
codeframe/fn_lo.py
codeframe/fn_load.py
codeframe/fn_print.py
codeframe/fn_show.py
codeframe/installation.py
codeframe/interpreter.py
codeframe/key_enter.py
codeframe/mmapwr.py
codeframe/objects.py
codeframe/topbar.py
codeframe/version.py
codeframe.egg-info/PKG-INFO
codeframe.egg-info/SOURCES.txt
codeframe.egg-info/dependency_links.txt
codeframe.egg-info/requires.txt
codeframe.egg-info/top_level.txt
codeframe/data/installation_files/.bumpversion.cfg
codeframe/data/installation_files/.gitignore
codeframe/data/installation_files/README.org
codeframe/data/installation_files/bin_codeframe.py
codeframe/data/installation_files/distcheck.sh
codeframe/data/installation_files/requirements.txt
codeframe/data/installation_files/setup.py
codeframe/data/installation_files/bin/codeframe
codeframe/data/installation_files/codeframe/__init__.py