Metadata-Version: 2.1
Name: codeframe
Version: 0.5.23
Summary: Automatically created environment for python package
Home-page: https://gitlab.com/jaromrax/codeframe
Author: me
Author-email: jaromrax@gmail.com
License: GPL2
